coremltools/__init__.py
coremltools/__main__.py
coremltools/_deps/__init__.py
coremltools/_scripts/__init__.py
coremltools/_scripts/converter.py
coremltools/converters/__init__.py
coremltools/converters/caffe/__init__.py
coremltools/converters/caffe/_caffe_converter.py
coremltools/converters/keras/__init__.py
coremltools/converters/keras/_keras2_converter.py
coremltools/converters/keras/_keras_converter.py
coremltools/converters/keras/_layers.py
coremltools/converters/keras/_layers2.py
coremltools/converters/keras/_topology.py
coremltools/converters/keras/_topology2.py
coremltools/converters/keras/_utils.py
coremltools/converters/libsvm/__init__.py
coremltools/converters/libsvm/_libsvm_converter.py
coremltools/converters/libsvm/_libsvm_util.py
coremltools/converters/sklearn/_LinearSVC.py
coremltools/converters/sklearn/_LinearSVR.py
coremltools/converters/sklearn/_NuSVC.py
coremltools/converters/sklearn/_NuSVR.py
coremltools/converters/sklearn/_SVC.py
coremltools/converters/sklearn/_SVR.py
coremltools/converters/sklearn/__init__.py
coremltools/converters/sklearn/_converter.py
coremltools/converters/sklearn/_converter_internal.py
coremltools/converters/sklearn/_decision_tree_classifier.py
coremltools/converters/sklearn/_decision_tree_regressor.py
coremltools/converters/sklearn/_dict_vectorizer.py
coremltools/converters/sklearn/_gradient_boosting_classifier.py
coremltools/converters/sklearn/_gradient_boosting_regressor.py
coremltools/converters/sklearn/_imputer.py
coremltools/converters/sklearn/_linear_regression.py
coremltools/converters/sklearn/_logistic_regression.py
coremltools/converters/sklearn/_normalizer.py
coremltools/converters/sklearn/_one_hot_encoder.py
coremltools/converters/sklearn/_random_forest_classifier.py
coremltools/converters/sklearn/_random_forest_regressor.py
coremltools/converters/sklearn/_sklearn_util.py
coremltools/converters/sklearn/_standard_scaler.py
coremltools/converters/sklearn/_svm_common.py
coremltools_windows-2.1.0.dist-info/LICENSE.txt
coremltools_windows-2.1.0.dist-info/METADATA
coremltools_windows-2.1.0.dist-info/WHEEL
coremltools_windows-2.1.0.dist-info/entry_points.txt
coremltools_windows-2.1.0.dist-info/top_level.txt
coremltools_windows-2.1.0.dist-info/RECORD
