Metadata-Version: 2.1
Name: coremltools-windows
Version: 2.1.0
Summary: Community Tools for CoreML
Home-page: UNKNOWN
Author: Apple Inc.
Author-email: coremltools@apple.com
License: BSD
Platform: UNKNOWN
Classifier: Development Status :: 4 - Beta
Classifier: Intended Audience :: End Users/Desktop
Classifier: Intended Audience :: Developers
Classifier: Operating System :: MacOS :: MacOS X
Classifier: Programming Language :: Python :: 2.7
Classifier: Programming Language :: Python :: 3.5
Classifier: Programming Language :: Python :: 3.6
Classifier: Topic :: Scientific/Engineering
Classifier: Topic :: Software Development
Requires-Dist: numpy (>=1.10.0)
Requires-Dist: protobuf (>=3.1.0)
Requires-Dist: six (>=1.10.0)
